TorchSisso/FeatureSpaceConstruction.py
TorchSisso/SISSORegressor.py
TorchSisso/SISSO_REGRESSOR_TORCH.py
TorchSisso/SISSO_model.py
TorchSisso/__init__.py
TorchSisso/testRegressor.py
TorchSisso-1.1.1.dist-info/METADATA
TorchSisso-1.1.1.dist-info/WHEEL
TorchSisso-1.1.1.dist-info/top_level.txt
TorchSisso-1.1.1.dist-info/RECORD
