Metadata-Version: 2.1
Name: TorchSisso
Version: 1.1.1
Summary: GPU Supported Sure Independence Screening and Sparsifying Operator Package
Home-page: https://github.com/MR1319/TorchSisso
Author: Madhav Muthyala
Author-email: madhavreddymuthyala@gmail.com
Classifier: Programming Language :: Python :: 3
Classifier: License :: OSI Approved :: MIT License
Classifier: Operating System :: OS Independent
Requires-Python: >=3.6
Requires-Dist: torch
Requires-Dist: pandas
Requires-Dist: numpy
